c3/__init__.py
c3/__main__.py
c3/certentry.py
c3/commandline.py
c3/constants.py
c3/errors.py
c3/getpassword.py
c3/keypairs.py
c3/parsedate.py
c3/pass_protect.py
c3/signverify.py
c3/structure.py
c3/textfiles.py
c3/tests/__init__.py
c3/tests/fuzz_glitch.py
c3/tests/test_all.py
c3sign-1.1.5.data/data/LICENSE.txt
c3sign-1.1.5.dist-info/AUTHORS
c3sign-1.1.5.dist-info/LICENSE.txt
c3sign-1.1.5.dist-info/METADATA
c3sign-1.1.5.dist-info/WHEEL
c3sign-1.1.5.dist-info/entry_points.txt
c3sign-1.1.5.dist-info/top_level.txt
c3sign-1.1.5.dist-info/RECORD
