Metadata-Version: 2.1
Name: c3sign
Version: 1.1.5
Summary: Compact Crypto Certs (C3) is a mini-PKI signer/verifier with full chain functionality and compact binary and friendly text cert formats
Home-page: https://github.com/oddy/c3
Author: Beau Butler
Author-email: beau.butler@gmail.com
License: MIT
Classifier: License :: OSI Approved :: MIT License
Classifier: Programming Language :: Python :: 2.7
Classifier: Programming Language :: Python :: 3
Classifier: Development Status :: 5 - Production/Stable
License-File: LICENSE.txt
License-File: AUTHORS
Requires-Dist: b3buf
Requires-Dist: ecdsa
Requires-Dist: PyNaCl
